{
    "Objective": "Component Inspection",
    "Board Name": "hc-06",
    "Algorithm": [
        {
            "color": [],
            "corner": []
        },
        {
            "color": [
                {
                    "part_id": "10002311",
                    "number of neurons": 512,
                    "vector length": 64,
                    "accuracy": "98"
                }
            ]
        },
        {
            "color": [
                {
                    "part_id": "10002312",
                    "number of neurons": 512,
                    "vector length": 64,
                    "accuracy": "24"
                }
            ]
        },
        {
            "corner": [
                {
                    "part_id": "10002311",
                    "number of neurons": 512,
                    "vector length": 64,
                    "accuracy": "60"
                }
            ]
        },
        {
            "corner": [
                {
                    "part_id": "10002312",
                    "number of neurons": 512,
                    "vector length": 64,
                    "accuracy": "73"
                }
            ]
        },
        {
            "color": [
                {
                    "part_id": "10002311",
                    "number of neurons": 256.0,
                    "vector length": 128,
                    "accuracy": "98"
                }
            ]
        },
        {
            "color": [
                {
                    "part_id": "10002312",
                    "number of neurons": 256.0,
                    "vector length": 128,
                    "accuracy": "24"
                }
            ]
        },
        {
            "corner": [
                {
                    "part_id": "10002311",
                    "number of neurons": 256.0,
                    "vector length": 128,
                    "accuracy": "89"
                }
            ]
        },
        {
            "corner": [
                {
                    "part_id": "10002312",
                    "number of neurons": 256.0,
                    "vector length": 128,
                    "accuracy": "73"
                }
            ]
        },
        {
            "color": [
                {
                    "part_id": "10002311",
                    "number of neurons": 128.0,
                    "vector length": 256,
                    "accuracy": "98"
                }
            ]
        },
        {
            "color": [
                {
                    "part_id": "10002312",
                    "number of neurons": 128.0,
                    "vector length": 256,
                    "accuracy": "24"
                }
            ]
        },
        {
            "color": [
                {
                    "part_id": "10002311",
                    "number of neurons": 64.0,
                    "vector length": 512,
                    "accuracy": "98"
                }
            ]
        },
        {
            "color": [
                {
                    "part_id": "10002312",
                    "number of neurons": 64.0,
                    "vector length": 512,
                    "accuracy": "24"
                }
            ]
        }
    ]
}